{"name":"Popush项目技术博客","tagline":"by 张佳瑜 From **“少爷吉祥”**——小组","body":"Popush部署体会\r\n==========\r\n\r\n张佳瑜 2014-10-12\r\n------------------\r\n\r\n#任务\r\nlinux系统部署\r\n\r\n#部署体会\r\n我觉得部署过程基本没遇到什么问题。开始时java部署遇到一点问题，由于机器上之前安装了jdk8,编译jdk7时环境变量没有完全改过来。按照则明说的方法配了一遍，把/usr/bin/java指向java7,成功解决。  \r\n然后是不知道要node app.js  \r\n然后是没看到.doc上的那部分文档，卡了很久，上群里问了一下才知道。  \r\n然后就成功发布了。不过很多功能都无效。用root权限运行node app.js成功解决。\r\n\r\n张佳瑜 2014-10-12\r\n---------------\r\n#大作业分工\r\n部署\r\n#感想\r\n嗯我要认真地部署这个程序。可能我们现在的程序都没有什么，随随便便就部署出去了。真正的商业网站需要很强的稳定性，部署应该是非常重要的。","google":"","note":"Don't delete this file! It's used internally to help with page regeneration."}